MANIFEST.in
README.rst
_javabridge.c
_javabridge_mac.c
_javabridge_nomac.c
mac_javabridge_utils.c
mac_javabridge_utils.h
setup.cfg
setup.py
strtoull.c
java/org_cellprofiler_javabridge_CPython.c
java/org_cellprofiler_javabridge_CPython.h
java/org/cellprofiler/findlibjvm.java
java/org/cellprofiler/javabridge/CPython.java
java/org/cellprofiler/javabridge/CPythonInvocationHandler.java
java/org/cellprofiler/javabridge/test/RealRect.java
java/org/cellprofiler/javabridge/test/TestCPython.java
java/org/cellprofiler/runnablequeue/RunnableQueue.java
java/org/cellprofiler/runnablequeue/TestRunnableQueue.java
javabridge/__init__.py
javabridge/_version.py
javabridge/jutil.py
javabridge/locate.py
javabridge/noseplugin.py
javabridge/wrappers.py
javabridge.egg-info/PKG-INFO
javabridge.egg-info/SOURCES.txt
javabridge.egg-info/dependency_links.txt
javabridge.egg-info/entry_points.txt
javabridge.egg-info/requires.txt
javabridge.egg-info/top_level.txt
javabridge/jars/cpython.jar
javabridge/jars/libjava2cpython.so
javabridge/jars/rhino-1.7R4.jar
javabridge/jars/runnablequeue.jar
javabridge/jars/test.jar
javabridge/tests/__init__.py
javabridge/tests/test_cpython.py
javabridge/tests/test_javabridge.py
javabridge/tests/test_jutil.py
javabridge/tests/test_wrappers.py