Metadata-Version: 1.1
Name: javabridge
Version: 1.0.17
Summary: Python wrapper for the Java Native Interface
Home-page: http://github.com/CellProfiler/python-javabridge/
Author: UNKNOWN
Author-email: UNKNOWN
License: BSD License
Platform: UNKNOWN
Classifier: Development Status :: 5 - Production/Stable
Classifier: License :: OSI Approved :: BSD License
Classifier: Programming Language :: Java
Classifier: Programming Language :: Python :: 2
Classifier: Programming Language :: Python :: 3
